README.md
setup.py
cyxmltv/__init__.py
cyxmltv/__main__.py
cyxmltv/common.py
cyxmltv/parser.py
cyxmltv/version.py
cyxmltv/xmltv.py
cyxmltv.egg-info/PKG-INFO
cyxmltv.egg-info/SOURCES.txt
cyxmltv.egg-info/dependency_links.txt
cyxmltv.egg-info/entry_points.txt
cyxmltv.egg-info/requires.txt
cyxmltv.egg-info/top_level.txt