Metadata-Version: 2.1
Name: cyxmltv
Version: 0.3
Summary: Command line utility to create an XmlTv formatted EPG for cypriot channels
Home-page: UNKNOWN
Author: Harry Papaxenopoulos
Author-email: hpapaxen@gmail.com
License: MIT
Keywords: cyprus xmltv plex cypriot epg rik1 rik
Platform: UNKNOWN
Classifier: Programming Language :: Python :: 3
Classifier: License :: OSI Approved :: MIT License
Classifier: Operating System :: OS Independent
